torbjorn/__init__.py
torbjorn/main.py
torbjorn/test_main.py
torbjorn/utils.py
torbjorn/utils_test.py
torbjorn-0.1.1.dist-info/LICENSE
torbjorn-0.1.1.dist-info/METADATA
torbjorn-0.1.1.dist-info/WHEEL
torbjorn-0.1.1.dist-info/top_level.txt
torbjorn-0.1.1.dist-info/zip-safe
torbjorn-0.1.1.dist-info/RECORD
