Metadata-Version: 2.1
Name: torbjorn
Version: 0.1.1
Summary: Provide some practical Python decorators.
Home-page: https://github.com/Ailln/torbjorn
Author: Ailln
Author-email: kinggreenhall@gmail.com
License: MIT License
Platform: UNKNOWN
Classifier: Programming Language :: Python :: 3
Classifier: License :: OSI Approved :: MIT License
Classifier: Operating System :: OS Independent
Requires-Python: >=3.6
License-File: LICENSE
Requires-Dist: setuptools (>=49.6.0)
